pyezxl/__init__.py
pyezxl/pyezenum.py
pyezxl/pyezre.py
pyezxl/pyeztime.py
pyezxl/pyezxl.py
pyezxl/excel_addin/pyezxl_addin_20210502.xla
pyezxl/pyezxl_code/pyezxl_100_add_text_at_left_01.py
pyezxl/pyezxl_code/pyezxl_100_add_text_at_right_01.py
pyezxl/pyezxl_code/pyezxl_100_add_text_n_step_01.py
pyezxl/pyezxl_code/pyezxl_100_insert_column_new_01.py
pyezxl/pyezxl_code/pyezxl_100_insert_newrow_n_times_01.py
pyezxl/pyezxl_code/pyezxl_110_fill_empty_cell_as_above_value_01.py
pyezxl/pyezxl_code/pyezxl_110_insert_column_new_01.py
pyezxl/pyezxl_code/pyezxl_110_insert_newrow_n_times_01.py
pyezxl/pyezxl_code/pyezxl_120_change_text_all_small_01.py
pyezxl/pyezxl_code/pyezxl_120_change_text_first_capital_01.py
pyezxl/pyezxl_code/pyezxl_120_change_text_swap_small_capital_01.py
pyezxl/pyezxl_code/pyezxl_120_change_text_to_cap_01.py
pyezxl/pyezxl_code/pyezxl_120_replace_values_many_words_at_once_01.py
pyezxl/pyezxl_code/pyezxl_130_delete_all_line_drawing_01.py
pyezxl/pyezxl_code/pyezxl_130_delete_continious_samevalue_02.py
pyezxl/pyezxl_code/pyezxl_130_delete_empty_line_01.py
pyezxl/pyezxl_code/pyezxl_130_delete_from_n_words_01.py
pyezxl/pyezxl_code/pyezxl_130_delete_line_when_same_multi_columns_01.py
pyezxl/pyezxl_code/pyezxl_130_delete_n_step_01.py
pyezxl/pyezxl_code/pyezxl_130_delete_name_one_01.py
pyezxl/pyezxl_code/pyezxl_130_delete_number_in_text_01.py
pyezxl/pyezxl_code/pyezxl_130_delete_rangename_all_01.py
pyezxl/pyezxl_code/pyezxl_130_delete_samedata_03.py
pyezxl/pyezxl_code/pyezxl_130_delete_samedata_at_same_position_01.py
pyezxl/pyezxl_code/pyezxl_130_delete_space_both_side_01.py
pyezxl/pyezxl_code/pyezxl_130_delete_space_left_side_01.py
pyezxl/pyezxl_code/pyezxl_130_delete_space_right_side_01.py
pyezxl/pyezxl_code/pyezxl_130_delete_values_between_specific_words_01.py
pyezxl/pyezxl_code/pyezxl_140_fill_empty_cell_as_above_value_01.py
pyezxl/pyezxl_code/pyezxl_150_copy_one_line_to_another_sheet_01.py
pyezxl/pyezxl_code/pyezxl_200_count_paint_empty_cell_01.py
pyezxl-1.6.4.dist-info/METADATA
pyezxl-1.6.4.dist-info/WHEEL
pyezxl-1.6.4.dist-info/top_level.txt
pyezxl-1.6.4.dist-info/RECORD
