Metadata-Version: 2.1
Name: pyezxl
Version: 1.6.4
Summary: Easily Read / Write Excel using Python
Home-page: https://www.halmoney.com
Author: sjpark
Author-email: sjpkorea@yahoo.com
License: UNKNOWN
Download-URL: https://github.com/sjpark/pyezxl/archive/v1.6.4.tar.gz
Platform: UNKNOWN
Classifier: Programming Language :: Python :: 3
Classifier: License :: OSI Approved :: GNU General Public License v3 (GPLv3)
Classifier: Operating System :: Microsoft :: Windows
Requires-Python: >=3.5
